LICENSE
MANIFEST.in
README
setup.py
bin/pystatic
pystatic/__init__.py
pystatic/pystatic.py
pystatic.egg-info/PKG-INFO
pystatic.egg-info/SOURCES.txt
pystatic.egg-info/dependency_links.txt
pystatic.egg-info/requires.txt
pystatic.egg-info/top_level.txt
pystatic/project/assets/css/bootstrap-responsive.css
pystatic/project/assets/css/bootstrap.css
pystatic/project/assets/css/custom.css
pystatic/project/assets/fonts/fontawesome-webfont.eot
pystatic/project/assets/fonts/fontawesome-webfont.svg
pystatic/project/assets/fonts/fontawesome-webfont.ttf
pystatic/project/assets/fonts/fontawesome-webfont.woff
pystatic/project/assets/img/glyphicons-halflings-white.png
pystatic/project/assets/img/glyphicons-halflings.png
pystatic/project/assets/js/bootstrap-alert.js
pystatic/project/assets/js/bootstrap-button.js
pystatic/project/assets/js/bootstrap-carousel.js
pystatic/project/assets/js/bootstrap-collapse.js
pystatic/project/assets/js/bootstrap-dropdown.js
pystatic/project/assets/js/bootstrap-modal.js
pystatic/project/assets/js/bootstrap-popover.js
pystatic/project/assets/js/bootstrap-scrollspy.js
pystatic/project/assets/js/bootstrap-tab.js
pystatic/project/assets/js/bootstrap-tooltip.js
pystatic/project/assets/js/bootstrap-transition.js
pystatic/project/assets/js/bootstrap-typeahead.js
pystatic/project/assets/js/jquery-1.8.1.min.js
pystatic/project/assets/js/google-code-prettify/prettify.css
pystatic/project/assets/js/google-code-prettify/prettify.js
pystatic/project/conf/vars.yaml
pystatic/project/output/.placeholder
pystatic/project/templates/_base.html
pystatic/project/templates/index.html